Metadata-Version: 1.0
Name: anti-forgetful
Version: 18.4.24.4
Summary: UNKNOWN
Home-page: https://github.com/tbenthompson/anti_forgetful
Author: T. Ben Thompson
Author-email: t.ben.thompson@gmail.com
License: MIT
Platform: any
